{"assets/Braslets.jpeg":["assets/Braslets.jpeg"],"assets/Earings.jpeg":["assets/Earings.jpeg"],"assets/bangles.jpeg":["assets/bangles.jpeg"],"assets/bg.png":["assets/bg.png"],"assets/default.png":["assets/default.png"],"assets/logo(1).png":["assets/logo(1).png"],"assets/logo.jpeg":["assets/logo.jpeg"],"assets/necklace.jpeg":["assets/necklace.jpeg"],"assets/pendats.jpeg":["assets/pendats.jpeg"],"assets/register.png":["assets/register.png"],"assets/ring1.png":["assets/ring1.png"],"packages/cupertino_icons/assets/CupertinoIcons.ttf":["packages/cupertino_icons/assets/CupertinoIcons.ttf"]}